{"statuses": [{"created_at": "Mon Oct 30 19:04:31 +0000 2017", "id": 925075964287246337, "id_str": "925075964287246337", "text": "Queijo por cima ponto p apple mas a alface n pode ficar assim em contato com a carne entao empatado https://t.co/hr6XDTegr3", "truncated": false, "entities": {"hashtags": [], "symbols": [], "user_mentions": [], "urls": [{"url": "https://t.co/hr6XDTegr3", "expanded_url": "https://twitter.com/momentsbrasil/status/925055148333912064", "display_url": "twitter.com/momentsbrasil/\u2026", "indices": [100, 123]}]}, "metadata": {"iso_language_code": "pt", "result_type": "recent"}, "source": "<a href=\"http://twitter.com/download/iphone\" rel=\"nofollow\">Twitter for iPhone</a>", "in_reply_to_status_id": null, "in_reply_to_status_id_str": null, "in_reply_to_user_id": null, "in_reply_to_user_id_str": null, "in_reply_to_screen_name": null, "user": {"id": 2788485614, "id_str": "2788485614", "name": "thailseween\ud83c\udf83", "screen_name": "cerealforme", "location": "Brasil", "description": "Hey! | 18 | She/Her | Pan | INFP | Neutral Good | Stirlingite | \u2728\ud83e\udd40\ud83c\udf38\ud83c\udf3e Lindsey follows!", "url": null, "entities": {"description": {"urls": []}}, "protected": false, "followers_count": 778, "friends_count": 502, "listed_count": 0, "created_at": "Wed Sep 03 19:30:59 +0000 2014", "favourites_count": 45226, "utc_offset": -7200, "time_zone": "Brasilia", "geo_enabled": false, "verified": false, "statuses_count": 19724, "lang": "pt", "contributors_enabled": false, "is_translator": false, "is_translation_enabled": false, "profile_background_color": "131516", "profile_background_image_url": "http://abs.twimg.com/images/themes/theme14/bg.gif", "profile_background_image_url_https": "https://abs.twimg.com/images/themes/theme14/bg.gif", "profile_background_tile": true, "profile_image_url": "http://pbs.twimg.com/profile_images/924050438370021376/P05Ypn3K_normal.jpg", "profile_image_url_https": "https://pbs.twimg.com/profile_images/924050438370021376/P05Ypn3K_normal.jpg", "profile_banner_url": "https://pbs.twimg.com/profile_banners/2788485614/1503749099", "profile_link_color": "009999", "profile_sidebar_border_color": "EEEEEE", "profile_sidebar_fill_color": "EFEFEF", "profile_text_color": "333333", "profile_use_background_image": true, "has_extended_profile": true, "default_profile": false, "default_profile_image": false, "following": false, "follow_request_sent": false, "notifications": false, "translator_type": "none"}, "geo": null, "coordinates": null, "place": null, "contributors": null, "is_quote_status": true, "quoted_status_id": 925055148333912064, "quoted_status_id_str": "925055148333912064", "quoted_status": {"created_at": "Mon Oct 30 17:41:48 +0000 2017", "id": 925055148333912064, "id_str": "925055148333912064", "text": "\u26a1\ufe0fDepois da briga 'arroz ou feij\u00e3o por baixo', a posi\u00e7\u00e3o do queijo no hamb\u00farguer \u00e9 a pol\u00eamica do momento\ud83c\udf54\ud83d\ude02\nhttps://t.co/WTVRtl6NXI", "truncated": false, "entities": {"hashtags": [], "symbols": [], "user_mentions": [], "urls": [{"url": "https://t.co/WTVRtl6NXI", "expanded_url": "https://twitter.com/i/moments/925046336076091393", "display_url": "twitter.com/i/moments/9250\u2026", "indices": [107, 130]}]}, "metadata": {"iso_language_code": "pt", "result_type": "recent"}, "source": "<a href=\"http://twitter.com\" rel=\"nofollow\">Twitter Web Client</a>", "in_reply_to_status_id": null, "in_reply_to_status_id_str": null, "in_reply_to_user_id": null, "in_reply_to_user_id_str": null, "in_reply_to_screen_name": null, "user": {"id": 4172587277, "id_str": "4172587277", "name": "Moments Brasil", "screen_name": "momentsbrasil", "location": "S\u00e3o Paulo, Brasil", "description": "O melhor do que est\u00e1 acontecendo no Twitter em um instante. Siga seus eventos favoritos e receba Tweets em tempo real na sua timeline. #Moments\u26a1\ufe0f", "url": "https://t.co/yLQOHaByM2", "entities": {"url": {"urls": [{"url": "https://t.co/yLQOHaByM2", "expanded_url": "https://blog.twitter.com/pt/2015/como-os-tweets-viram-moments-manual-de-curadoria-e-princ-pios", "display_url": "blog.twitter.com/pt/2015/como-o\u2026", "indices": [0, 23]}]}, "description": {"urls": []}}, "protected": false, "followers_count": 467528, "friends_count": 9, "listed_count": 1084, "created_at": "Thu Nov 12 16:46:02 +0000 2015", "favourites_count": 743, "utc_offset": -7200, "time_zone": "Brasilia", "geo_enabled": true, "verified": true, "statuses_count": 37195, "lang": "pt", "contributors_enabled": false, "is_translator": false, "is_translation_enabled": false, "profile_background_color": "000000", "profile_background_image_url": "http://abs.twimg.com/images/themes/theme1/bg.png", "profile_background_image_url_https": "https://abs.twimg.com/images/themes/theme1/bg.png", "profile_background_tile": false, "profile_image_url": "http://pbs.twimg.com/profile_images/666324297489739776/nyQKZybh_normal.png", "profile_image_url_https": "https://pbs.twimg.com/profile_images/666324297489739776/nyQKZybh_normal.png", "profile_banner_url": "https://pbs.twimg.com/profile_banners/4172587277/1447699082", "profile_link_color": "292F33", "profile_sidebar_border_color": "000000", "profile_sidebar_fill_color": "000000", "profile_text_color": "000000", "profile_use_background_image": false, "has_extended_profile": false, "default_profile": false, "default_profile_image": false, "following": false, "follow_request_sent": false, "notifications": false, "translator_type": "none"}, "geo": null, "coordinates": null, "place": null, "contributors": null, "is_quote_status": false, "retweet_count": 4, "favorite_count": 34, "favorited": false, "retweeted": false, "possibly_sensitive": false, "lang": "pt"}, "retweet_count": 1, "favorite_count": 0, "favorited": false, "retweeted": false, "possibly_sensitive": false, "lang": "pt"}, {"created_at": "Mon Oct 30 19:04:31 +0000 2017", "id": 925075963041415173, "id_str": "925075963041415173", "text": "RT @ellieeewbu: ATTENTION ALL GIRLS ALL GIRLS!!! Go to your photos and type in the \u2018Brassiere\u2019 why are apple saving these and made it a fol\u2026", "truncated": false, "entities": {"hashtags": [], "symbols": [], "user_mentions": [{"screen_name": "ellieeewbu", "name": "ell", "id": 198176904, "id_str": "198176904", "indices": [3, 14]}], "urls": []}, "metadata": {"iso_language_code": "en", "result_type": "recent"}, "source": "<a href=\"http://twitter.com/download/iphone\" rel=\"nofollow\">Twitter for iPhone</a>", "in_reply_to_status_id": null, "in_reply_to_status_id_str": null, "in_reply_to_user_id": null, "in_reply_to_user_id_str": null, "in_reply_to_screen_name": null, "user": {"id": 372011477, "id_str": "372011477", "name": "mona lisa saperstein", "screen_name": "penacolada_", "location": "Manhattan, NY", "description": "xicana y salvadore\u00f1a | #BLM | Venmo and CashApp: penaacolada | NYU", "url": null, "entities": {"description": {"urls": []}}, "protected": false, "followers_count": 524, "friends_count": 558, "listed_count": 4, "created_at": "Sun Sep 11 23:29:47 +0000 2011", "favourites_count": 19583, "utc_offset": -25200, "time_zone": "Pacific Time (US & Canada)", "geo_enabled": true, "verified": false, "statuses_count": 27612, "lang": "en", "contributors_enabled": false, "is_translator": false, "is_translation_enabled": false, "profile_background_color": "36081A", "profile_background_image_url": "http://pbs.twimg.com/profile_background_images/442826993281679360/N1QkYJUE.jpeg", "profile_background_image_url_https": "https://pbs.twimg.com/profile_background_images/442826993281679360/N1QkYJUE.jpeg", "profile_background_tile": true, "profile_image_url": "http://pbs.twimg.com/profile_images/886621878596509696/IfYe2y4v_normal.jpg", "profile_image_url_https": "https://pbs.twimg.com/profile_images/886621878596509696/IfYe2y4v_normal.jpg", "profile_banner_url": "https://pbs.twimg.com/profile_banners/372011477/1471020804", "profile_link_color": "981CEB", "profile_sidebar_border_color": "FFFFFF", "profile_sidebar_fill_color": "CDCF9F", "profile_text_color": "E37F54", "profile_use_background_image": true, "has_extended_profile": true, "default_profile": false, "default_profile_image": false, "following": false, "follow_request_sent": false, "notifications": false, "translator_type": "none"}, "geo": null, "coordinates": null, "place": null, "contributors": null, "retweeted_status": {"created_at": "Mon Oct 30 15:53:40 +0000 2017", "id": 925027935119118342, "id_str": "925027935119118342", "text": "ATTENTION ALL GIRLS ALL GIRLS!!! Go to your photos and type in the \u2018Brassiere\u2019 why are apple saving these and made it a folder!!?!!?\ud83d\ude31\ud83d\ude31\ud83d\ude31\ud83d\ude31", "truncated": false, "entities": {"hashtags": [], "symbols": [], "user_mentions": [], "urls": []}, "metadata": {"iso_language_code": "en", "result_type": "recent"}, "source": "<a href=\"http://twitter.com/download/iphone\" rel=\"nofollow\">Twitter for iPhone</a>", "in_reply_to_status_id": null, "in_reply_to_status_id_str": null, "in_reply_to_user_id": null, "in_reply_to_user_id_str": null, "in_reply_to_screen_name": null, "user": {"id": 198176904, "id_str": "198176904", "name": "ell", "screen_name": "ellieeewbu", "location": "Cyprus", "description": "@_samherbs \u2661  elliescales3@hotmail.com", "url": "https://t.co/B8BXWlLguT", "entities": {"url": {"urls": [{"url": "https://t.co/B8BXWlLguT", "expanded_url": "https://Instagram.com/ellieeewbu/", "display_url": "Instagram.com/ellieeewbu/", "indices": [0, 23]}]}, "description": {"urls": []}}, "protected": false, "followers_count": 19180, "friends_count": 2671, "listed_count": 33, "created_at": "Sun Oct 03 15:31:17 +0000 2010", "favourites_count": 10928, "utc_offset": 3600, "time_zone": "Amsterdam", "geo_enabled": false, "verified": false, "statuses_count": 34933, "lang": "en", "contributors_enabled": false, "is_translator": false, "is_translation_enabled": false, "profile_background_color": "0099B9", "profile_background_image_url": "http://pbs.twimg.com/profile_background_images/378800000086055051/38e63017ed16e2592b8bdd04f0e46748.jpeg", "profile_background_image_url_https": "https://pbs.twimg.com/profile_background_images/378800000086055051/38e63017ed16e2592b8bdd04f0e46748.jpeg", "profile_background_tile": true, "profile_image_url": "http://pbs.twimg.com/profile_images/924693446883004416/C6twJ6oN_normal.jpg", "profile_image_url_https": "https://pbs.twimg.com/profile_images/924693446883004416/C6twJ6oN_normal.jpg", "profile_banner_url": "https://pbs.twimg.com/profile_banners/198176904/1504529004", "profile_link_color": "0099B9", "profile_sidebar_border_color": "FFFFFF", "profile_sidebar_fill_color": "95E8EC", "profile_text_color": "3C3940", "profile_use_background_image": true, "has_extended_profile": true, "default_profile": false, "default_profile_image": false, "following": false, "follow_request_sent": false, "notifications": false, "translator_type": "none"}, "geo": null, "coordinates": null, "place": null, "contributors": null, "is_quote_status": false, "retweet_count": 1507, "favorite_count": 2039, "favorited": false, "retweeted": false, "lang": "en"}, "is_quote_status": false, "retweet_count": 1507, "favorite_count": 0, "favorited": false, "retweeted": false, "lang": "en"}, {"created_at": "Mon Oct 30 19:04:31 +0000 2017", "id": 925075962978594816, "id_str": "925075962978594816", "text": "Westlaw : Download the Westlaw app today https://t.co/qr6OfEONgS https://t.co/9hpKbBnO10 (via Twitter\u2026 https://t.co/w2TFeFiejB", "truncated": true, "entities": {"hashtags": [], "symbols": [], "user_mentions": [], "urls": [{"url": "https://t.co/qr6OfEONgS", "expanded_url": "http://tmsnrt.rs/2igPLXq", "display_url": "tmsnrt.rs/2igPLXq", "indices": [41, 64]}, {"url": "https://t.co/w2TFeFiejB", "expanded_url": "https://twitter.com/i/web/status/925075962978594816", "display_url": "twitter.com/i/web/status/9\u2026", "indices": [103, 126]}], "media": [{"id": 925075592709521409, "id_str": "925075592709521409", "indices": [65, 88], "media_url": "http://pbs.twimg.com/media/DNaHWa3VwAEHdpw.jpg", "media_url_https": "https://pbs.twimg.com/media/DNaHWa3VwAEHdpw.jpg", "url": "https://t.co/9hpKbBnO10", "display_url": "pic.twitter.com/9hpKbBnO10", "expanded_url": "https://twitter.com/Westlaw/status/925075597482647552/photo/1", "type": "photo", "sizes": {"small": {"w": 440, "h": 220, "resize": "fit"}, "medium": {"w": 440, "h": 220, "resize": "fit"}, "large": {"w": 440, "h": 220, "resize": "fit"}, "thumb": {"w": 150, "h": 150, "resize": "crop"}}, "source_status_id": 925075597482647552, "source_status_id_str": "925075597482647552", "source_user_id": 15307378, "source_user_id_str": "15307378"}]}, "extended_entities": {"media": [{"id": 925075592709521409, "id_str": "925075592709521409", "indices": [65, 88], "media_url": "http://pbs.twimg.com/media/DNaHWa3VwAEHdpw.jpg", "media_url_https": "https://pbs.twimg.com/media/DNaHWa3VwAEHdpw.jpg", "url": "https://t.co/9hpKbBnO10", "display_url": "pic.twitter.com/9hpKbBnO10", "expanded_url": "https://twitter.com/Westlaw/status/925075597482647552/photo/1", "type": "photo", "sizes": {"small": {"w": 440, "h": 220, "resize": "fit"}, "medium": {"w": 440, "h": 220, "resize": "fit"}, "large": {"w": 440, "h": 220, "resize": "fit"}, "thumb": {"w": 150, "h": 150, "resize": "crop"}}, "source_status_id": 925075597482647552, "source_status_id_str": "925075597482647552", "source_user_id": 15307378, "source_user_id_str": "15307378"}]}, "metadata": {"iso_language_code": "en", "result_type": "recent"}, "source": "<a href=\"https://ifttt.com\" rel=\"nofollow\">IFTTT</a>", "in_reply_to_status_id": null, "in_reply_to_status_id_str": null, "in_reply_to_user_id": null, "in_reply_to_user_id_str": null, "in_reply_to_screen_name": null, "user": {"id": 213803022, "id_str": "213803022", "name": "Susan C. Freeman", "screen_name": "susfree", "location": "HI to CA to LA to MA", "description": "Passionate, honest, solution-oriented. Very good writer, pretty good wife & bomb of a mom. For MARCOM, POLITICS & TRAVEL PICS, FOLLOW ME! Opinions are mine.", "url": "https://t.co/N9JfGiRRtH", "entities": {"url": {"urls": [{"url": "https://t.co/N9JfGiRRtH", "expanded_url": "http://www.linkedin.com/in/susancfreeman", "display_url": "linkedin.com/in/susancfreem\u2026", "indices": [0, 23]}]}, "description": {"urls": []}}, "protected": false, "followers_count": 1168, "friends_count": 2297, "listed_count": 304, "created_at": "Tue Nov 09 20:58:24 +0000 2010", "favourites_count": 7236, "utc_offset": -25200, "time_zone": "Pacific Time (US & Canada)", "geo_enabled": true, "verified": false, "statuses_count": 40984, "lang": "en", "contributors_enabled": false, "is_translator": false, "is_translation_enabled": false, "profile_background_color": "C0DEED", "profile_background_image_url": "http://abs.twimg.com/images/themes/theme1/bg.png", "profile_background_image_url_https": "https://abs.twimg.com/images/themes/theme1/bg.png", "profile_background_tile": false, "profile_image_url": "http://pbs.twimg.com/profile_images/737319050699636737/grhj499A_normal.jpg", "profile_image_url_https": "https://pbs.twimg.com/profile_images/737319050699636737/grhj499A_normal.jpg", "profile_banner_url": "https://pbs.twimg.com/profile_banners/213803022/1454968832", "profile_link_color": "1DA1F2", "profile_sidebar_border_color": "C0DEED", "profile_sidebar_fill_color": "DDEEF6", "profile_text_color": "333333", "profile_use_background_image": true, "has_extended_profile": false, "default_profile": true, "default_profile_image": false, "following": false, "follow_request_sent": false, "notifications": false, "translator_type": "none"}, "geo": null, "coordinates": null, "place": null, "contributors": null, "is_quote_status": true, "quoted_status_id": 925075597482647552, "quoted_status_id_str": "925075597482647552", "quoted_status": {"created_at": "Mon Oct 30 19:03:04 +0000 2017", "id": 925075597482647552, "id_str": "925075597482647552", "text": "Download the Westlaw app today https://t.co/9zZoVzLkPn https://t.co/zfL0CRiK2y", "truncated": false, "entities": {"hashtags": [], "symbols": [], "user_mentions": [], "urls": [{"url": "https://t.co/9zZoVzLkPn", "expanded_url": "http://tmsnrt.rs/2igPLXq", "display_url": "tmsnrt.rs/2igPLXq", "indices": [31, 54]}], "media": [{"id": 925075592709521409, "id_str": "925075592709521409", "indices": [55, 78], "media_url": "http://pbs.twimg.com/media/DNaHWa3VwAEHdpw.jpg", "media_url_https": "https://pbs.twimg.com/media/DNaHWa3VwAEHdpw.jpg", "url": "https://t.co/zfL0CRiK2y", "display_url": "pic.twitter.com/zfL0CRiK2y", "expanded_url": "https://twitter.com/Westlaw/status/925075597482647552/photo/1", "type": "photo", "sizes": {"small": {"w": 440, "h": 220, "resize": "fit"}, "medium": {"w": 440, "h": 220, "resize": "fit"}, "large": {"w": 440, "h": 220, "resize": "fit"}, "thumb": {"w": 150, "h": 150, "resize": "crop"}}}]}, "extended_entities": {"media": [{"id": 925075592709521409, "id_str": "925075592709521409", "indices": [55, 78], "media_url": "http://pbs.twimg.com/media/DNaHWa3VwAEHdpw.jpg", "media_url_https": "https://pbs.twimg.com/media/DNaHWa3VwAEHdpw.jpg", "url": "https://t.co/zfL0CRiK2y", "display_url": "pic.twitter.com/zfL0CRiK2y", "expanded_url": "https://twitter.com/Westlaw/status/925075597482647552/photo/1", "type": "photo", "sizes": {"small": {"w": 440, "h": 220, "resize": "fit"}, "medium": {"w": 440, "h": 220, "resize": "fit"}, "large": {"w": 440, "h": 220, "resize": "fit"}, "thumb": {"w": 150, "h": 150, "resize": "crop"}}}]}, "metadata": {"iso_language_code": "en", "result_type": "recent"}, "source": "<a href=\"http://adobe.com\" rel=\"nofollow\">Adobe\u00ae Social</a>", "in_reply_to_status_id": null, "in_reply_to_status_id_str": null, "in_reply_to_user_id": null, "in_reply_to_user_id_str": null, "in_reply_to_screen_name": null, "user": {"id": 15307378, "id_str": "15307378", "name": "Westlaw", "screen_name": "Westlaw", "location": "Minnesota", "description": "Providing information about legal research, law practice management, Westlaw & legal news.", "url": "https://t.co/ThDkcqfeDX", "entities": {"url": {"urls": [{"url": "https://t.co/ThDkcqfeDX", "expanded_url": "http://legalsolutions.thomsonreuters.com/law-products/westlaw-legal-research/", "display_url": "legalsolutions.thomsonreuters.com/law-products/w\u2026", "indices": [0, 23]}]}, "description": {"urls": []}}, "protected": false, "followers_count": 37372, "friends_count": 1075, "listed_count": 912, "created_at": "Thu Jul 03 11:55:21 +0000 2008", "favourites_count": 605, "utc_offset": -18000, "time_zone": "Central Time (US & Canada)", "geo_enabled": false, "verified": true, "statuses_count": 15675, "lang": "en", "contributors_enabled": false, "is_translator": false, "is_translation_enabled": false, "profile_background_color": "1A3F9E", "profile_background_image_url": "http://pbs.twimg.com/profile_background_images/74663304/L-355324_twitterBG.png", "profile_background_image_url_https": "https://pbs.twimg.com/profile_background_images/74663304/L-355324_twitterBG.png", "profile_background_tile": false, "profile_image_url": "http://pbs.twimg.com/profile_images/843919757464166400/IiBKXC_Q_normal.jpg", "profile_image_url_https": "https://pbs.twimg.com/profile_images/843919757464166400/IiBKXC_Q_normal.jpg", "profile_banner_url": "https://pbs.twimg.com/profile_banners/15307378/1490041221", "profile_link_color": "F0A23B", "profile_sidebar_border_color": "060804", "profile_sidebar_fill_color": "F5FAF9", "profile_text_color": "636563", "profile_use_background_image": true, "has_extended_profile": false, "default_profile": false, "default_profile_image": false, "following": false, "follow_request_sent": false, "notifications": false, "translator_type": "none"}, "geo": null, "coordinates": null, "place": null, "contributors": null, "is_quote_status": false, "retweet_count": 0, "favorite_count": 0, "favorited": false, "retweeted": false, "possibly_sensitive": false, "lang": "en"}, "retweet_count": 0, "favorite_count": 0, "favorited": false, "retweeted": false, "possibly_sensitive": false, "lang": "en"}, {"created_at": "Mon Oct 30 19:04:31 +0000 2017", "id": 925075962907291649, "id_str": "925075962907291649", "text": "Apple licencie un ing\u00e9nieur pour avoir laiss\u00e9 sa fille filmer l'iPhone X\u00a0 \u00e0 la cantine https://t.co/VqcZvuvseH https://t.co/JXXkrGOUdE", "truncated": false, "entities": {"hashtags": [], "symbols": [], "user_mentions": [], "urls": [{"url": "https://t.co/VqcZvuvseH", "expanded_url": "http://ebx.sh/2hnGlty", "display_url": "ebx.sh/2hnGlty", "indices": [87, 110]}], "media": [{"id": 925075958692044800, "id_str": "925075958692044800", "indices": [111, 134], "media_url": "http://pbs.twimg.com/media/DNaHruQX4AADrFK.jpg", "media_url_https": "https://pbs.twimg.com/media/DNaHruQX4AADrFK.jpg", "url": "https://t.co/JXXkrGOUdE", "display_url": "pic.twitter.com/JXXkrGOUdE", "expanded_url": "https://twitter.com/BFM_HighTech/status/925075962907291649/photo/1", "type": "photo", "sizes": {"medium": {"w": 600, "h": 429, "resize": "fit"}, "thumb": {"w": 150, "h": 150, "resize": "crop"}, "large": {"w": 600, "h": 429, "resize": "fit"}, "small": {"w": 600, "h": 429, "resize": "fit"}}}]}, "extended_entities": {"media": [{"id": 925075958692044800, "id_str": "925075958692044800", "indices": [111, 134], "media_url": "http://pbs.twimg.com/media/DNaHruQX4AADrFK.jpg", "media_url_https": "https://pbs.twimg.com/media/DNaHruQX4AADrFK.jpg", "url": "https://t.co/JXXkrGOUdE", "display_url": "pic.twitter.com/JXXkrGOUdE", "expanded_url": "https://twitter.com/BFM_HighTech/status/925075962907291649/photo/1", "type": "photo", "sizes": {"medium": {"w": 600, "h": 429, "resize": "fit"}, "thumb": {"w": 150, "h": 150, "resize": "crop"}, "large": {"w": 600, "h": 429, "resize": "fit"}, "small": {"w": 600, "h": 429, "resize": "fit"}}}]}, "metadata": {"iso_language_code": "fr", "result_type": "recent"}, "source": "<a href=\"https://www.echobox.com\" rel=\"nofollow\">Echobox Social</a>", "in_reply_to_status_id": null, "in_reply_to_status_id_str": null, "in_reply_to_user_id": null, "in_reply_to_user_id_str": null, "in_reply_to_screen_name": null, "user": {"id": 4156055837, "id_str": "4156055837", "name": "BFM High-Tech", "screen_name": "BFM_HighTech", "location": "France", "description": "Toute l'actualit\u00e9 des nouvelles technologies sur BFM Business", "url": "https://t.co/vumHbo1iZt", "entities": {"url": {"urls": [{"url": "https://t.co/vumHbo1iZt", "expanded_url": "http://bfmbusiness.bfmtv.com/hightech/", "display_url": "bfmbusiness.bfmtv.com/hightech/", "indices": [0, 23]}]}, "description": {"urls": []}}, "protected": false, "followers_count": 2886, "friends_count": 137, "listed_count": 68, "created_at": "Tue Nov 10 11:22:19 +0000 2015", "favourites_count": 3, "utc_offset": null, "time_zone": null, "geo_enabled": false, "verified": true, "statuses_count": 2768, "lang": "fr", "contributors_enabled": false, "is_translator": false, "is_translation_enabled": false, "profile_background_color": "000000", "profile_background_image_url": "http://abs.twimg.com/images/themes/theme1/bg.png", "profile_background_image_url_https": "https://abs.twimg.com/images/themes/theme1/bg.png", "profile_background_tile": false, "profile_image_url": "http://pbs.twimg.com/profile_images/875728290765565952/C_6R8b5t_normal.jpg", "profile_image_url_https": "https://pbs.twimg.com/profile_images/875728290765565952/C_6R8b5t_normal.jpg", "profile_banner_url": "https://pbs.twimg.com/profile_banners/4156055837/1448618058", "profile_link_color": "1277C9", "profile_sidebar_border_color": "000000", "profile_sidebar_fill_color": "000000", "profile_text_color": "000000", "profile_use_background_image": false, "has_extended_profile": true, "default_profile": false, "default_profile_image": false, "following": false, "follow_request_sent": false, "notifications": false, "translator_type": "none"}, "geo": null, "coordinates": null, "place": null, "contributors": null, "is_quote_status": false, "retweet_count": 0, "favorite_count": 0, "favorited": false, "retweeted": false, "possibly_sensitive": false, "lang": "fr"}, {"created_at": "Mon Oct 30 19:04:30 +0000 2017", "id": 925075961552494592, "id_str": "925075961552494592", "text": "RT @BTS_twt: You can listen to #RM and @Wale 's Change on iTunes, Spotify &amp; Tidal.\n\nhttps://t.co/i2jr33D8PA", "truncated": false, "entities": {"hashtags": [{"text": "RM", "indices": [31, 34]}], "symbols": [], "user_mentions": [{"screen_name": "BTS_twt", "name": "\ubc29\ud0c4\uc18c\ub144\ub2e8", "id": 335141638, "id_str": "335141638", "indices": [3, 11]}, {"screen_name": "Wale", "name": "Wale", "id": 17929027, "id_str": "17929027", "indices": [39, 44]}], "urls": [{"url": "https://t.co/i2jr33D8PA", "expanded_url": "https://itunes.apple.com/us/album/change-single/id1300042938", "display_url": "itunes.apple.com/us/album/chang\u2026", "indices": [88, 111]}]}, "metadata": {"iso_language_code": "en", "result_type": "recent"}, "source": "<a href=\"http://twitter.com/download/iphone\" rel=\"nofollow\">Twitter for iPhone</a>", "in_reply_to_status_id": null, "in_reply_to_status_id_str": null, "in_reply_to_user_id": null, "in_reply_to_user_id_str": null, "in_reply_to_screen_name": null, "user": {"id": 2806944641, "id_str": "2806944641", "name": "UU", "screen_name": "nambyjn", "location": "", "description": "--you can\u2019t control my shit--", "url": null, "entities": {"description": {"urls": []}}, "protected": false, "followers_count": 462, "friends_count": 259, "listed_count": 10, "created_at": "Sun Oct 05 07:04:00 +0000 2014", "favourites_count": 2483, "utc_offset": -25200, "time_zone": "Pacific Time (US & Canada)", "geo_enabled": false, "verified": false, "statuses_count": 63066, "lang": "fr", "contributors_enabled": false, "is_translator": false, "is_translation_enabled": false, "profile_background_color": "000000", "profile_background_image_url": "http://pbs.twimg.com/profile_background_images/669964683747676161/r6dCMXSp.jpg", "profile_background_image_url_https": "https://pbs.twimg.com/profile_background_images/669964683747676161/r6dCMXSp.jpg", "profile_background_tile": true, "profile_image_url": "http://pbs.twimg.com/profile_images/916725247163985920/bJM3Qs4B_normal.jpg", "profile_image_url_https": "https://pbs.twimg.com/profile_images/916725247163985920/bJM3Qs4B_normal.jpg", "profile_banner_url": "https://pbs.twimg.com/profile_banners/2806944641/1496349920", "profile_link_color": "FABE7F", "profile_sidebar_border_color": "000000", "profile_sidebar_fill_color": "000000", "profile_text_color": "000000", "profile_use_background_image": true, "has_extended_profile": true, "default_profile": false, "default_profile_image": false, "following": false, "follow_request_sent": false, "notifications": false, "translator_type": "none"}, "geo": null, "coordinates": null, "place": null, "contributors": null, "retweeted_status": {"created_at": "Mon Oct 30 06:36:21 +0000 2017", "id": 924887682978910208, "id_str": "924887682978910208", "text": "You can listen to #RM and @Wale 's Change on iTunes, Spotify &amp; Tidal.\n\nhttps://t.co/i2jr33D8PA", "truncated": false, "entities": {"hashtags": [{"text": "RM", "indices": [18, 21]}], "symbols": [], "user_mentions": [{"screen_name": "Wale", "name": "Wale", "id": 17929027, "id_str": "17929027", "indices": [26, 31]}], "urls": [{"url": "https://t.co/i2jr33D8PA", "expanded_url": "https://itunes.apple.com/us/album/change-single/id1300042938", "display_url": "itunes.apple.com/us/album/chang\u2026", "indices": [75, 98]}]}, "metadata": {"iso_language_code": "en", "result_type": "recent"}, "source": "<a href=\"http://twitter.com/download/iphone\" rel=\"nofollow\">Twitter for iPhone</a>", "in_reply_to_status_id": null, "in_reply_to_status_id_str": null, "in_reply_to_user_id": null, "in_reply_to_user_id_str": null, "in_reply_to_screen_name": null, "user": {"id": 335141638, "id_str": "335141638", "name": "\ubc29\ud0c4\uc18c\ub144\ub2e8", "screen_name": "BTS_twt", "location": "", "description": "Hi~ we are BTS!", "url": "https://t.co/BP579N8Xkk", "entities": {"url": {"urls": [{"url": "https://t.co/BP579N8Xkk", "expanded_url": "http://btsblog.ibighit.com", "display_url": "btsblog.ibighit.com", "indices": [0, 23]}]}, "description": {"urls": []}}, "protected": false, "followers_count": 9615624, "friends_count": 86, "listed_count": 21084, "created_at": "Thu Jul 14 06:32:56 +0000 2011", "favourites_count": 60, "utc_offset": 28800, "time_zone": "Irkutsk", "geo_enabled": true, "verified": true, "statuses_count": 10238, "lang": "ko", "contributors_enabled": false, "is_translator": false, "is_translation_enabled": false, "profile_background_color": "FFFFFF", "profile_background_image_url": "http://abs.twimg.com/images/themes/theme14/bg.gif", "profile_background_image_url_https": "https://abs.twimg.com/images/themes/theme14/bg.gif", "profile_background_tile": false, "profile_image_url": "http://pbs.twimg.com/profile_images/905808134727286784/nn7m8q1p_normal.jpg", "profile_image_url_https": "https://pbs.twimg.com/profile_images/905808134727286784/nn7m8q1p_normal.jpg", "profile_banner_url": "https://pbs.twimg.com/profile_banners/335141638/1504796451", "profile_link_color": "FF0000", "profile_sidebar_border_color": "FFFFFF", "profile_sidebar_fill_color": "EFEFEF", "profile_text_color": "333333", "profile_use_background_image": true, "has_extended_profile": false, "default_profile": false, "default_profile_image": false, "following": false, "follow_request_sent": false, "notifications": false, "translator_type": "regular"}, "geo": null, "coordinates": null, "place": null, "contributors": null, "is_quote_status": false, "retweet_count": 81014, "favorite_count": 210262, "favorited": false, "retweeted": false, "possibly_sensitive": false, "lang": "en"}, "is_quote_status": false, "retweet_count": 81014, "favorite_count": 0, "favorited": false, "retweeted": false, "possibly_sensitive": false, "lang": "en"}, {"created_at": "Mon Oct 30 19:04:30 +0000 2017", "id": 925075961514733568, "id_str": "925075961514733568", "text": "Apple iPad with Retina Display MD513LL/A (16GB, Wi-Fi, White) 4th Generation (Certified Refurbished)\u2026 https://t.co/vHIgGmGSZl", "truncated": true, "entities": {"hashtags": [], "symbols": [], "user_mentions": [], "urls": [{"url": "https://t.co/vHIgGmGSZl", "expanded_url": "https://twitter.com/i/web/status/925075961514733568", "display_url": "twitter.com/i/web/status/9\u2026", "indices": [102, 125]}]}, "metadata": {"iso_language_code": "en", "result_type": "recent"}, "source": "<a href=\"https://ifttt.com\" rel=\"nofollow\">IFTTT</a>", "in_reply_to_status_id": null, "in_reply_to_status_id_str": null, "in_reply_to_user_id": null, "in_reply_to_user_id_str": null, "in_reply_to_screen_name": null, "user": {"id": 2574547706, "id_str": "2574547706", "name": "#weightlossprogram", "screen_name": "joerafel", "location": "United States", "description": "Find Best Weight Loss Plans for Guaranteed Results in Few Days https://t.co/he0josqiBk", "url": "https://t.co/he0josqiBk", "entities": {"url": {"urls": [{"url": "https://t.co/he0josqiBk", "expanded_url": "http://most-successful-weight-loss-program.blogspot.com/", "display_url": "\u2026sful-weight-loss-program.blogspot.com", "indices": [0, 23]}]}, "description": {"urls": [{"url": "https://t.co/he0josqiBk", "expanded_url": "http://most-successful-weight-loss-program.blogspot.com/", "display_url": "\u2026sful-weight-loss-program.blogspot.com", "indices": [63, 86]}]}}, "protected": false, "followers_count": 4580, "friends_count": 4551, "listed_count": 126, "created_at": "Wed Jun 18 10:04:31 +0000 2014", "favourites_count": 126, "utc_offset": 19800, "time_zone": "New Delhi", "geo_enabled": true, "verified": false, "statuses_count": 96162, "lang": "en", "contributors_enabled": false, "is_translator": false, "is_translation_enabled": false, "profile_background_color": "C0DEED", "profile_background_image_url": "http://abs.twimg.com/images/themes/theme1/bg.png", "profile_background_image_url_https": "https://abs.twimg.com/images/themes/theme1/bg.png", "profile_background_tile": false, "profile_image_url": "http://pbs.twimg.com/profile_images/660064143332904960/cnumvcA5_normal.jpg", "profile_image_url_https": "https://pbs.twimg.com/profile_images/660064143332904960/cnumvcA5_normal.jpg", "profile_banner_url": "https://pbs.twimg.com/profile_banners/2574547706/1464759162", "profile_link_color": "1DA1F2", "profile_sidebar_border_color": "C0DEED", "profile_sidebar_fill_color": "DDEEF6", "profile_text_color": "333333", "profile_use_background_image": true, "has_extended_profile": false, "default_profile": true, "default_profile_image": false, "following": false, "follow_request_sent": false, "notifications": false, "translator_type": "none"}, "geo": null, "coordinates": null, "place": null, "contributors": null, "is_quote_status": false, "retweet_count": 0, "favorite_count": 0, "favorited": false, "retweeted": false, "possibly_sensitive": false, "lang": "en"}, {"created_at": "Mon Oct 30 19:04:30 +0000 2017", "id": 925075960810168320, "id_str": "925075960810168320", "text": "RT @PatentJosh: Some thoughts on the test Judge Koh will apply in the new Apple-Samsung trial.  (Not a fan.) https://t.co/dEXhEqnHi0", "truncated": false, "entities": {"hashtags": [], "symbols": [], "user_mentions": [{"screen_name": "PatentJosh", "name": "Joshua Landau", "id": 864701899542601729, "id_str": "864701899542601729", "indices": [3, 14]}], "urls": [{"url": "https://t.co/dEXhEqnHi0", "expanded_url": "https://twitter.com/PatentProgress/status/925068612385296386", "display_url": "twitter.com/PatentProgress\u2026", "indices": [109, 132]}]}, "metadata": {"iso_language_code": "en", "result_type": "recent"}, "source": "<a href=\"https://about.twitter.com/products/tweetdeck\" rel=\"nofollow\">TweetDeck</a>", "in_reply_to_status_id": null, "in_reply_to_status_id_str": null, "in_reply_to_user_id": null, "in_reply_to_user_id_str": null, "in_reply_to_screen_name": null, "user": {"id": 2214832435, "id_str": "2214832435", "name": "Michael Loney", "screen_name": "mdloney", "location": "New York", "description": "Americas editor @managingIP, tweets on intellectual property - patents, trademarks, copyright\nLinkedIn: http://t.co/l3WsUz1cjS\nGroup: http://t.co/7Oc2E22CCP", "url": "http://t.co/HipLRRHQI5", "entities": {"url": {"urls": [{"url": "http://t.co/HipLRRHQI5", "expanded_url": "http://www.managingip.com", "display_url": "managingip.com", "indices": [0, 22]}]}, "description": {"urls": [{"url": "http://t.co/l3WsUz1cjS", "expanded_url": "http://linkd.in/18CLYK5", "display_url": "linkd.in/18CLYK5", "indices": [104, 126]}, {"url": "http://t.co/7Oc2E22CCP", "expanded_url": "http://linkd.in/1jDltWo", "display_url": "linkd.in/1jDltWo", "indices": [134, 156]}]}}, "protected": false, "followers_count": 2222, "friends_count": 1307, "listed_count": 71, "created_at": "Mon Nov 25 23:33:19 +0000 2013", "favourites_count": 66, "utc_offset": null, "time_zone": null, "geo_enabled": false, "verified": false, "statuses_count": 4187, "lang": "en", "contributors_enabled": false, "is_translator": false, "is_translation_enabled": false, "profile_background_color": "C0DEED", "profile_background_image_url": "http://abs.twimg.com/images/themes/theme1/bg.png", "profile_background_image_url_https": "https://abs.twimg.com/images/themes/theme1/bg.png", "profile_background_tile": false, "profile_image_url": "http://pbs.twimg.com/profile_images/378800000790949601/25b8b1cf8edf00745b37757340040056_normal.jpeg", "profile_image_url_https": "https://pbs.twimg.com/profile_images/378800000790949601/25b8b1cf8edf00745b37757340040056_normal.jpeg", "profile_banner_url": "https://pbs.twimg.com/profile_banners/2214832435/1398285889", "profile_link_color": "1DA1F2", "profile_sidebar_border_color": "C0DEED", "profile_sidebar_fill_color": "DDEEF6", "profile_text_color": "333333", "profile_use_background_image": true, "has_extended_profile": false, "default_profile": true, "default_profile_image": false, "following": false, "follow_request_sent": false, "notifications": false, "translator_type": "none"}, "geo": null, "coordinates": null, "place": null, "contributors": null, "retweeted_status": {"created_at": "Mon Oct 30 18:40:20 +0000 2017", "id": 925069875822972930, "id_str": "925069875822972930", "text": "Some thoughts on the test Judge Koh will apply in the new Apple-Samsung trial.  (Not a fan.) https://t.co/dEXhEqnHi0", "truncated": false, "entities": {"hashtags": [], "symbols": [], "user_mentions": [], "urls": [{"url": "https://t.co/dEXhEqnHi0", "expanded_url": "https://twitter.com/PatentProgress/status/925068612385296386", "display_url": "twitter.com/PatentProgress\u2026", "indices": [93, 116]}]}, "metadata": {"iso_language_code": "en", "result_type": "recent"}, "source": "<a href=\"http://tapbots.com/software/tweetbot/mac\" rel=\"nofollow\">Tweetbot for Mac</a>", "in_reply_to_status_id": null, "in_reply_to_status_id_str": null, "in_reply_to_user_id": null, "in_reply_to_user_id_str": null, "in_reply_to_screen_name": null, "user": {"id": 864701899542601729, "id_str": "864701899542601729", "name": "Joshua Landau", "screen_name": "PatentJosh", "location": "DC | joshua.s.landau@gmail.com", "description": "Attorney, advocate, snow enthusiast.  Patent Counsel @CCIANet, lead blogger @PatentProgress, recovering litigator, all out patent nerd. All views are my own.", "url": "https://t.co/Ba9GjctpX2", "entities": {"url": {"urls": [{"url": "https://t.co/Ba9GjctpX2", "expanded_url": "https://www.patentprogress.org", "display_url": "patentprogress.org", "indices": [0, 23]}]}, "description": {"urls": []}}, "protected": false, "followers_count": 107, "friends_count": 87, "listed_count": 3, "created_at": "Wed May 17 04:39:33 +0000 2017", "favourites_count": 4, "utc_offset": -14400, "time_zone": "Eastern Time (US & Canada)", "geo_enabled": false, "verified": false, "statuses_count": 294, "lang": "en", "contributors_enabled": false, "is_translator": false, "is_translation_enabled": false, "profile_background_color": "F5F8FA", "profile_background_image_url": null, "profile_background_image_url_https": null, "profile_background_tile": false, "profile_image_url": "http://pbs.twimg.com/profile_images/864929592506712064/sgBh0eek_normal.jpg", "profile_image_url_https": "https://pbs.twimg.com/profile_images/864929592506712064/sgBh0eek_normal.jpg", "profile_banner_url": "https://pbs.twimg.com/profile_banners/864701899542601729/1508363969", "profile_link_color": "1DA1F2", "profile_sidebar_border_color": "C0DEED", "profile_sidebar_fill_color": "DDEEF6", "profile_text_color": "333333", "profile_use_background_image": true, "has_extended_profile": true, "default_profile": true, "default_profile_image": false, "following": false, "follow_request_sent": false, "notifications": false, "translator_type": "none"}, "geo": null, "coordinates": null, "place": null, "contributors": null, "is_quote_status": true, "quoted_status_id": 925068612385296386, "quoted_status_id_str": "925068612385296386", "quoted_status": {"created_at": "Mon Oct 30 18:35:18 +0000 2017", "id": 925068612385296386, "id_str": "925068612385296386", "text": "New Trial On Design Patent Damages, But A Flawed\u00a0Test https://t.co/HXq13pVPEg", "truncated": false, "entities": {"hashtags": [], "symbols": [], "user_mentions": [], "urls": [{"url": "https://t.co/HXq13pVPEg", "expanded_url": "https://www.patentprogress.org/2017/10/30/new-trial-design-patent-damages-flawed-test/", "display_url": "patentprogress.org/2017/10/30/new\u2026", "indices": [54, 77]}]}, "metadata": {"iso_language_code": "en", "result_type": "recent"}, "source": "<a href=\"http://publicize.wp.com/\" rel=\"nofollow\">WordPress.com</a>", "in_reply_to_status_id": null, "in_reply_to_status_id_str": null, "in_reply_to_user_id": null, "in_reply_to_user_id_str": null, "in_reply_to_screen_name": null, "user": {"id": 790043437, "id_str": "790043437", "name": "Patent Progress", "screen_name": "PatentProgress", "location": "Washington, DC", "description": "News and views on the US patent system and how to #fixpatents. The site includes a blog, a dictionary, and the Resource Center. Powered by @CCIAnet.", "url": "http://t.co/rsknj5AuH4", "entities": {"url": {"urls": [{"url": "http://t.co/rsknj5AuH4", "expanded_url": "http://www.patentprogress.org", "display_url": "patentprogress.org", "indices": [0, 22]}]}, "description": {"urls": []}}, "protected": false, "followers_count": 1968, "friends_count": 192, "listed_count": 70, "created_at": "Wed Aug 29 19:54:15 +0000 2012", "favourites_count": 724, "utc_offset": -14400, "time_zone": "Eastern Time (US & Canada)", "geo_enabled": false, "verified": false, "statuses_count": 3281, "lang": "en", "contributors_enabled": false, "is_translator": false, "is_translation_enabled": false, "profile_background_color": "0099B9", "profile_background_image_url": "http://abs.twimg.com/images/themes/theme4/bg.gif", "profile_background_image_url_https": "https://abs.twimg.com/images/themes/theme4/bg.gif", "profile_background_tile": false, "profile_image_url": "http://pbs.twimg.com/profile_images/2853542552/7eafd84155c1bf738c6f2a265c562e10_normal.png", "profile_image_url_https": "https://pbs.twimg.com/profile_images/2853542552/7eafd84155c1bf738c6f2a265c562e10_normal.png", "profile_banner_url": "https://pbs.twimg.com/profile_banners/790043437/1355337605", "profile_link_color": "0099B9", "profile_sidebar_border_color": "FFFFFF", "profile_sidebar_fill_color": "95E8EC", "profile_text_color": "3C3940", "profile_use_background_image": true, "has_extended_profile": false, "default_profile": false, "default_profile_image": false, "following": false, "follow_request_sent": false, "notifications": false, "translator_type": "none"}, "geo": null, "coordinates": null, "place": null, "contributors": null, "is_quote_status": false, "retweet_count": 0, "favorite_count": 0, "favorited": false, "retweeted": false, "possibly_sensitive": false, "lang": "en"}, "retweet_count": 3, "favorite_count": 2, "favorited": false, "retweeted": false, "possibly_sensitive": false, "lang": "en"}, "is_quote_status": true, "quoted_status_id": 925068612385296386, "quoted_status_id_str": "925068612385296386", "retweet_count": 3, "favorite_count": 0, "favorited": false, "retweeted": false, "possibly_sensitive": false, "lang": "en"}, {"created_at": "Mon Oct 30 19:04:30 +0000 2017", "id": 925075960675930112, "id_str": "925075960675930112", "text": "For real fruity fun in your hand try this app from #Reflex Gaming! https://t.co/aIRrVgiehF https://t.co/TDl2vggIzt", "truncated": false, "entities": {"hashtags": [{"text": "Reflex", "indices": [51, 58]}], "symbols": [], "user_mentions": [], "urls": [{"url": "https://t.co/aIRrVgiehF", "expanded_url": "http://goo.gl/TU8gBa", "display_url": "goo.gl/TU8gBa", "indices": [67, 90]}], "media": [{"id": 925075955911217153, "id_str": "925075955911217153", "indices": [91, 114], "media_url": "http://pbs.twimg.com/media/DNaHrj5X0AEiDw4.jpg", "media_url_https": "https://pbs.twimg.com/media/DNaHrj5X0AEiDw4.jpg", "url": "https://t.co/TDl2vggIzt", "display_url": "pic.twitter.com/TDl2vggIzt", "expanded_url": "https://twitter.com/spunk1979/status/925075960675930112/photo/1", "type": "photo", "sizes": {"thumb": {"w": 150, "h": 150, "resize": "crop"}, "medium": {"w": 768, "h": 1024, "resize": "fit"}, "large": {"w": 768, "h": 1024, "resize": "fit"}, "small": {"w": 510, "h": 680, "resize": "fit"}}}]}, "extended_entities": {"media": [{"id": 925075955911217153, "id_str": "925075955911217153", "indices": [91, 114], "media_url": "http://pbs.twimg.com/media/DNaHrj5X0AEiDw4.jpg", "media_url_https": "https://pbs.twimg.com/media/DNaHrj5X0AEiDw4.jpg", "url": "https://t.co/TDl2vggIzt", "display_url": "pic.twitter.com/TDl2vggIzt", "expanded_url": "https://twitter.com/spunk1979/status/925075960675930112/photo/1", "type": "photo", "sizes": {"thumb": {"w": 150, "h": 150, "resize": "crop"}, "medium": {"w": 768, "h": 1024, "resize": "fit"}, "large": {"w": 768, "h": 1024, "resize": "fit"}, "small": {"w": 510, "h": 680, "resize": "fit"}}}]}, "metadata": {"iso_language_code": "en", "result_type": "recent"}, "source": "<a href=\"https://example.com\" rel=\"nofollow\">ReflexPubFruit</a>", "in_reply_to_status_id": null, "in_reply_to_status_id_str": null, "in_reply_to_user_id": null, "in_reply_to_user_id_str": null, "in_reply_to_screen_name": null, "user": {"id": 751278043, "id_str": "751278043", "name": "Stephen Naylor", "screen_name": "spunk1979", "location": "", "description": "", "url": null, "entities": {"description": {"urls": []}}, "protected": false, "followers_count": 522, "friends_count": 1448, "listed_count": 2, "created_at": "Sat Aug 11 13:32:57 +0000 2012", "favourites_count": 6, "utc_offset": null, "time_zone": null, "geo_enabled": true, "verified": false, "statuses_count": 1655, "lang": "en", "contributors_enabled": false, "is_translator": false, "is_translation_enabled": false, "profile_background_color": "C0DEED", "profile_background_image_url": "http://abs.twimg.com/images/themes/theme1/bg.png", "profile_background_image_url_https": "https://abs.twimg.com/images/themes/theme1/bg.png", "profile_background_tile": false, "profile_image_url": "http://pbs.twimg.com/profile_images/2495032630/image_normal.jpg", "profile_image_url_https": "https://pbs.twimg.com/profile_images/2495032630/image_normal.jpg", "profile_link_color": "1DA1F2", "profile_sidebar_border_color": "C0DEED", "profile_sidebar_fill_color": "DDEEF6", "profile_text_color": "333333", "profile_use_background_image": true, "has_extended_profile": false, "default_profile": true, "default_profile_image": false, "following": false, "follow_request_sent": false, "notifications": false, "translator_type": "none"}, "geo": null, "coordinates": null, "place": null, "contributors": null, "is_quote_status": false, "retweet_count": 0, "favorite_count": 0, "favorited": false, "retweeted": false, "possibly_sensitive": false, "lang": "en"}, {"created_at": "Mon Oct 30 19:04:30 +0000 2017", "id": 925075959233081345, "id_str": "925075959233081345", "text": "#TRUEPIC already being used in over 100 #countries from #Argentina to #Zimbabwe; download free app now https://t.co/UpDVOdnWhY", "truncated": false, "entities": {"hashtags": [{"text": "TRUEPIC", "indices": [0, 8]}, {"text": "countries", "indices": [40, 50]}, {"text": "Argentina", "indices": [56, 66]}, {"text": "Zimbabwe", "indices": [70, 79]}], "symbols": [], "user_mentions": [], "urls": [{"url": "https://t.co/UpDVOdnWhY", "expanded_url": "https://itunes.apple.com/us/app/truepic/id1100089673?mt=8", "display_url": "itunes.apple.com/us/app/truepic\u2026", "indices": [103, 126]}]}, "metadata": {"iso_language_code": "en", "result_type": "recent"}, "source": "<a href=\"http://twitter.com\" rel=\"nofollow\">Twitter Web Client</a>", "in_reply_to_status_id": null, "in_reply_to_status_id_str": null, "in_reply_to_user_id": null, "in_reply_to_user_id_str": null, "in_reply_to_screen_name": null, "user": {"id": 833508468896079872, "id_str": "833508468896079872", "name": "truepicinc", "screen_name": "truepicinc", "location": "San Diego, CA", "description": "The Leader in Image Authenticity Certification", "url": "https://t.co/V7ORzCbdKC", "entities": {"url": {"urls": [{"url": "https://t.co/V7ORzCbdKC", "expanded_url": "http://truepic.com", "display_url": "truepic.com", "indices": [0, 23]}]}, "description": {"urls": []}}, "protected": false, "followers_count": 27, "friends_count": 123, "listed_count": 0, "created_at": "Mon Feb 20 02:47:59 +0000 2017", "favourites_count": 4, "utc_offset": null, "time_zone": null, "geo_enabled": false, "verified": false, "statuses_count": 72, "lang": "en", "contributors_enabled": false, "is_translator": false, "is_translation_enabled": false, "profile_background_color": "F5F8FA", "profile_background_image_url": null, "profile_background_image_url_https": null, "profile_background_tile": false, "profile_image_url": "http://pbs.twimg.com/profile_images/923934763982790656/pJM1v6LW_normal.jpg", "profile_image_url_https": "https://pbs.twimg.com/profile_images/923934763982790656/pJM1v6LW_normal.jpg", "profile_banner_url": "https://pbs.twimg.com/profile_banners/833508468896079872/1509118206", "profile_link_color": "1DA1F2", "profile_sidebar_border_color": "C0DEED", "profile_sidebar_fill_color": "DDEEF6", "profile_text_color": "333333", "profile_use_background_image": true, "has_extended_profile": false, "default_profile": true, "default_profile_image": false, "following": false, "follow_request_sent": false, "notifications": false, "translator_type": "none"}, "geo": null, "coordinates": null, "place": null, "contributors": null, "is_quote_status": false, "retweet_count": 0, "favorite_count": 0, "favorited": false, "retweeted": false, "possibly_sensitive": false, "lang": "en"}, {"created_at": "Mon Oct 30 19:04:30 +0000 2017", "id": 925075958134030342, "id_str": "925075958134030342", "text": "@maco67608327 \u3059\u3079\u3066\u3084\u3063\u305f\u306f\u305a\u306a\u306e\u306b\u306a\u30fc\uff3f|\uffe3|\u25cb\n\u3061\u3087\u3063\u3068\u30b8\u30cb\u30fc\u3068\u304b\u30cd\u30a4\u30d0\u30fc\u3068\u304b\u3082\u5229\u7528\u5238\u8cb7\u3048\u308b\u304b\u3069\u30fc\u304b\u3084\u3063\u3066\u307f\u308b\u308f\u30fc\uff61\uff9f(\uff9f\u00b4\u03c9`\uff9f)\uff9f\uff61\nApple Music\u89e3\u7d04\u3057\u3066\u518d\u5951\u7d04\u3059\u308c\u3070\u3053\u306e\u969b\u8a71\u306f\u3059\u307f\u305d\u3046\u3060\u306a\u30fc\u3068\u601d\u3063\u3066\u304d\u305fwww\n\u307e\u3053\u3061\u3083\u3093\u3042\u3068\u5c11\u3057\u671d\u307e\u3067\u304a\u3084\u3059\u307f\u301c\u2764\ufe0f", "truncated": false, "entities": {"hashtags": [], "symbols": [], "user_mentions": [{"screen_name": "maco67608327", "name": "maco sexy cool", "id": 760120760169959424, "id_str": "760120760169959424", "indices": [0, 13]}], "urls": []}, "metadata": {"iso_language_code": "ja", "result_type": "recent"}, "source": "<a href=\"http://twitter.com/download/iphone\" rel=\"nofollow\">Twitter for iPhone</a>", "in_reply_to_status_id": 925074551444094976, "in_reply_to_status_id_str": "925074551444094976", "in_reply_to_user_id": 760120760169959424, "in_reply_to_user_id_str": "760120760169959424", "in_reply_to_screen_name": "maco67608327", "user": {"id": 1304742415, "id_str": "1304742415", "name": "\ud1a0\ubaa8\ub274\ud83c\udf7c\u0295\u2022\u0361\u03c9\u2022\u0294", "screen_name": "05Rooooo", "location": "\u30aa\u30c8\u30ca\u30a2\u30ed\u30cf\u3068\u3082\u306b\u3085\ud83c\udf7c", "description": "\u0295\u2022\u1d25\u2022\u0294 #\uc544\uc2a4\ud2b8\ub85c #\uc724\uc0b0\ud558 #\ub530\ub098 \ud83c\udf7c\ud83d\udc9c\ud83d\udc96\ud83d\udc9c\ud83d\udc96\u30a2\u30b9\u30c8\u30ed\u7686\u3093\u306a\u30b9\u30ad\u0295\u2022\u0361\u03c9\u2022\u0294\ud83d\udc9c\ud83d\udc96\ud83d\udc9c\ud83d\udc96\ud83d\udd11\u30a2\u30b9\u30c8\u30ed\u5e0c\u671b\u306e\u661f\ud83d\udc9c\ud83d\udc96\ud83d\udc9c\ud83d\udc96", "url": null, "entities": {"description": {"urls": []}}, "protected": false, "followers_count": 31, "friends_count": 109, "listed_count": 0, "created_at": "Tue Mar 26 16:21:49 +0000 2013", "favourites_count": 1417, "utc_offset": 32400, "time_zone": "Tokyo", "geo_enabled": false, "verified": false, "statuses_count": 5067, "lang": "ja", "contributors_enabled": false, "is_translator": false, "is_translation_enabled": false, "profile_background_color": "000000", "profile_background_image_url": "http://abs.twimg.com/images/themes/theme1/bg.png", "profile_background_image_url_https": "https://abs.twimg.com/images/themes/theme1/bg.png", "profile_background_tile": false, "profile_image_url": "http://pbs.twimg.com/profile_images/878150459634065408/P8lneo_r_normal.jpg", "profile_image_url_https": "https://pbs.twimg.com/profile_images/878150459634065408/P8lneo_r_normal.jpg", "profile_banner_url": "https://pbs.twimg.com/profile_banners/1304742415/1501484826", "profile_link_color": "F58EA8", "profile_sidebar_border_color": "000000", "profile_sidebar_fill_color": "000000", "profile_text_color": "000000", "profile_use_background_image": false, "has_extended_profile": false, "default_profile": false, "default_profile_image": false, "following": false, "follow_request_sent": false, "notifications": false, "translator_type": "none"}, "geo": null, "coordinates": null, "place": null, "contributors": null, "is_quote_status": false, "retweet_count": 0, "favorite_count": 0, "favorited": false, "retweeted": false, "lang": "ja"}, {"created_at": "Mon Oct 30 19:04:29 +0000 2017", "id": 925075957282754562, "id_str": "925075957282754562", "text": "RT @falsaif: \u0634\u0628\u0627\u0628 \u0637\u0648\u0631\u0627 \u0644\u0639\u0628\u0647 \u0644\u062a\u0639\u0644\u064a\u0645 \u0627\u0644\u062d\u0631\u0648\u0641 \u0627\u0644\u0639\u0631\u0628\u064a\u0647 \u0644\u0639\u0645\u0631 \u0663 \u0627\u0644\u0649 \u0666 \u0633\u0646\u0648\u0627\u062a\n\n\u0648\u0627\u064a\u0636\u0627 \u0645\u062c\u0627\u0646\u064a\u0647\n\n\u0627\u0644\u0623\u0628\u0644 \u0633\u062a\u0648\u0631 https://t.co/rjgGnK47pz\n\n\u0627\u0644\u0623\u0646\u062f\u0631\u0648\u064a\u062f https://t\u2026", "truncated": false, "entities": {"hashtags": [], "symbols": [], "user_mentions": [{"screen_name": "falsaif", "name": "\u0641\u064a\u0635\u0644 \u0627\u0644\u0633\u064a\u0641", "id": 198028878, "id_str": "198028878", "indices": [3, 11]}], "urls": [{"url": "https://t.co/rjgGnK47pz", "expanded_url": "https://goo.gl/P4xqwq", "display_url": "goo.gl/P4xqwq", "indices": [95, 118]}]}, "metadata": {"iso_language_code": "ar", "result_type": "recent"}, "source": "<a href=\"http://twitter.com/download/iphone\" rel=\"nofollow\">Twitter for iPhone</a>", "in_reply_to_status_id": null, "in_reply_to_status_id_str": null, "in_reply_to_user_id": null, "in_reply_to_user_id_str": null, "in_reply_to_screen_name": null, "user": {"id": 1311015812, "id_str": "1311015812", "name": "\u0645\u062d\u0645\u062f \u0639\u0628\u062f\u0627\u0644\u0639\u0632\u064a\u0632 \u0645\u062d\u0645\u062f", "screen_name": "mhm4001", "location": "", "description": "", "url": null, "entities": {"description": {"urls": []}}, "protected": false, "followers_count": 781, "friends_count": 5001, "listed_count": 2, "created_at": "Thu Mar 28 15:50:25 +0000 2013", "favourites_count": 27157, "utc_offset": null, "time_zone": null, "geo_enabled": false, "verified": false, "statuses_count": 11066, "lang": "ar", "contributors_enabled": false, "is_translator": false, "is_translation_enabled": false, "profile_background_color": "C0DEED", "profile_background_image_url": "http://abs.twimg.com/images/themes/theme1/bg.png", "profile_background_image_url_https": "https://abs.twimg.com/images/themes/theme1/bg.png", "profile_background_tile": false, "profile_image_url": "http://pbs.twimg.com/profile_images/779810933677907968/Ptm2p6EE_normal.jpg", "profile_image_url_https": "https://pbs.twimg.com/profile_images/779810933677907968/Ptm2p6EE_normal.jpg", "profile_link_color": "1DA1F2", "profile_sidebar_border_color": "C0DEED", "profile_sidebar_fill_color": "DDEEF6", "profile_text_color": "333333", "profile_use_background_image": true, "has_extended_profile": false, "default_profile": true, "default_profile_image": false, "following": false, "follow_request_sent": false, "notifications": false, "translator_type": "none"}, "geo": null, "coordinates": null, "place": null, "contributors": null, "retweeted_status": {"created_at": "Wed Sep 13 19:10:02 +0000 2017", "id": 908045124109774848, "id_str": "908045124109774848", "text": "\u0634\u0628\u0627\u0628 \u0637\u0648\u0631\u0627 \u0644\u0639\u0628\u0647 \u0644\u062a\u0639\u0644\u064a\u0645 \u0627\u0644\u062d\u0631\u0648\u0641 \u0627\u0644\u0639\u0631\u0628\u064a\u0647 \u0644\u0639\u0645\u0631 \u0663 \u0627\u0644\u0649 \u0666 \u0633\u0646\u0648\u0627\u062a\n\n\u0648\u0627\u064a\u0636\u0627 \u0645\u062c\u0627\u0646\u064a\u0647\n\n\u0627\u0644\u0623\u0628\u0644 \u0633\u062a\u0648\u0631 https://t.co/rjgGnK47pz\n\n\u0627\u0644\u0623\u0646\u062f\u0631\u0648\u064a\u2026 https://t.co/Huw0eFPThS", "truncated": true, "entities": {"hashtags": [], "symbols": [], "user_mentions": [], "urls": [{"url": "https://t.co/rjgGnK47pz", "expanded_url": "https://goo.gl/P4xqwq", "display_url": "goo.gl/P4xqwq", "indices": [82, 105]}, {"url": "https://t.co/Huw0eFPThS", "expanded_url": "https://twitter.com/i/web/status/908045124109774848", "display_url": "twitter.com/i/web/status/9\u2026", "indices": [117, 140]}]}, "metadata": {"iso_language_code": "ar", "result_type": "recent"}, "source": "<a href=\"http://twitter.com/download/iphone\" rel=\"nofollow\">Twitter for iPhone</a>", "in_reply_to_status_id": null, "in_reply_to_status_id_str": null, "in_reply_to_user_id": null, "in_reply_to_user_id_str": null, "in_reply_to_screen_name": null, "user": {"id": 198028878, "id_str": "198028878", "name": "\u0641\u064a\u0635\u0644 \u0627\u0644\u0633\u064a\u0641", "screen_name": "falsaif", "location": "Riyadh ", "description": "Faisal Alsaif, Founder & CEO Tech Pills Productions\n \u0645\u0624\u0633\u0633 #\u062a\u064a\u0643_\u0628\u064a\u0644\u0632 \u0648\u062a\u0628\u0639\u0627\u062a\u0647\u0627\n \ninfo@tpprod.com\n\nSnap: FaisalTechPills", "url": "https://t.co/tFDZAJBHx6", "entities": {"url": {"urls": [{"url": "https://t.co/tFDZAJBHx6", "expanded_url": "http://www.youtube.com/uptodateksa2", "display_url": "youtube.com/uptodateksa2", "indices": [0, 23]}]}, "description": {"urls": []}}, "protected": false, "followers_count": 1188003, "friends_count": 919, "listed_count": 2034, "created_at": "Sun Oct 03 04:12:47 +0000 2010", "favourites_count": 1224, "utc_offset": 10800, "time_zone": "Riyadh", "geo_enabled": true, "verified": true, "statuses_count": 22395, "lang": "en", "contributors_enabled": false, "is_translator": false, "is_translation_enabled": false, "profile_background_color": "000000", "profile_background_image_url": "http://abs.twimg.com/images/themes/theme1/bg.png", "profile_background_image_url_https": "https://abs.twimg.com/images/themes/theme1/bg.png", "profile_background_tile": false, "profile_image_url": "http://pbs.twimg.com/profile_images/909129922924437507/jgbgZl2U_normal.jpg", "profile_image_url_https": "https://pbs.twimg.com/profile_images/909129922924437507/jgbgZl2U_normal.jpg", "profile_banner_url": "https://pbs.twimg.com/profile_banners/198028878/1454848538", "profile_link_color": "1B95E0", "profile_sidebar_border_color": "000000", "profile_sidebar_fill_color": "000000", "profile_text_color": "000000", "profile_use_background_image": false, "has_extended_profile": true, "default_profile": false, "default_profile_image": false, "following": false, "follow_request_sent": false, "notifications": false, "translator_type": "regular"}, "geo": null, "coordinates": null, "place": null, "contributors": null, "is_quote_status": false, "retweet_count": 176, "favorite_count": 498, "favorited": false, "retweeted": false, "possibly_sensitive": false, "lang": "ar"}, "is_quote_status": false, "retweet_count": 176, "favorite_count": 0, "favorited": false, "retweeted": false, "possibly_sensitive": false, "lang": "ar"}, {"created_at": "Mon Oct 30 19:04:29 +0000 2017", "id": 925075955919605762, "id_str": "925075955919605762", "text": "New iPhone Brings Face Recognition (and Fears) to the Masses: Apple will let you unlock the iPhone X with\u2026 https://t.co/305Hdu8Rbr #infosec", "truncated": false, "entities": {"hashtags": [{"text": "infosec", "indices": [131, 139]}], "symbols": [], "user_mentions": [], "urls": [{"url": "https://t.co/305Hdu8Rbr", "expanded_url": "https://goo.gl/fb/qA1sNW", "display_url": "goo.gl/fb/qA1sNW", "indices": [107, 130]}]}, "metadata": {"iso_language_code": "en", "result_type": "recent"}, "source": "<a href=\"http://www.google.com/\" rel=\"nofollow\">Google</a>", "in_reply_to_status_id": null, "in_reply_to_status_id_str": null, "in_reply_to_user_id": null, "in_reply_to_user_id_str": null, "in_reply_to_screen_name": null, "user": {"id": 420895831, "id_str": "420895831", "name": "IT Security News", "screen_name": "IT_securitynews", "location": "Worldwide", "description": "IT Security News aggregated. \r\nCreated by @SorinMustaca from manually chosen RSS feeds.", "url": "http://t.co/DBffQajj0W", "entities": {"url": {"urls": [{"url": "http://t.co/DBffQajj0W", "expanded_url": "http://www.itsecuritynews.info", "display_url": "itsecuritynews.info", "indices": [0, 22]}]}, "description": {"urls": []}}, "protected": false, "followers_count": 6804, "friends_count": 485, "listed_count": 731, "created_at": "Fri Nov 25 07:17:06 +0000 2011", "favourites_count": 0, "utc_offset": 3600, "time_zone": "Amsterdam", "geo_enabled": false, "verified": false, "statuses_count": 356894, "lang": "en", "contributors_enabled": false, "is_translator": false, "is_translation_enabled": false, "profile_background_color": "1A1B1F", "profile_background_image_url": "http://abs.twimg.com/images/themes/theme9/bg.gif", "profile_background_image_url_https": "https://abs.twimg.com/images/themes/theme9/bg.gif", "profile_background_tile": false, "profile_image_url": "http://pbs.twimg.com/profile_images/471630621161189376/_cgxYFxq_normal.png", "profile_image_url_https": "https://pbs.twimg.com/profile_images/471630621161189376/_cgxYFxq_normal.png", "profile_link_color": "2FC2EF", "profile_sidebar_border_color": "181A1E", "profile_sidebar_fill_color": "252429", "profile_text_color": "666666", "profile_use_background_image": true, "has_extended_profile": false, "default_profile": false, "default_profile_image": false, "following": false, "follow_request_sent": false, "notifications": false, "translator_type": "none"}, "geo": null, "coordinates": null, "place": null, "contributors": null, "is_quote_status": false, "retweet_count": 0, "favorite_count": 0, "favorited": false, "retweeted": false, "possibly_sensitive": false, "lang": "en"}, {"created_at": "Mon Oct 30 19:04:29 +0000 2017", "id": 925075953805594624, "id_str": "925075953805594624", "text": "RT @ANightOwlBlog: Spice up your fall with this delicious and easy Spiced Apple Rum Punch with @BundabergDrinks from @WorldMarket! #ad http\u2026", "truncated": false, "entities": {"hashtags": [{"text": "ad", "indices": [131, 134]}], "symbols": [], "user_mentions": [{"screen_name": "ANightOwlBlog", "name": "Kimberly Sneed", "id": 411110060, "id_str": "411110060", "indices": [3, 17]}, {"screen_name": "BundabergDrinks", "name": "Bundaberg Drinks", "id": 303639900, "id_str": "303639900", "indices": [95, 111]}, {"screen_name": "worldmarket", "name": "World Market", "id": 21553660, "id_str": "21553660", "indices": [117, 129]}], "urls": []}, "metadata": {"iso_language_code": "en", "result_type": "recent"}, "source": "<a href=\"https://roundteam.co\" rel=\"nofollow\">RoundTeam</a>", "in_reply_to_status_id": null, "in_reply_to_status_id_str": null, "in_reply_to_user_id": null, "in_reply_to_user_id_str": null, "in_reply_to_screen_name": null, "user": {"id": 298548658, "id_str": "298548658", "name": "Courtney O'Dell", "screen_name": "sweetcsdesigns", "location": "Loveland, CO", "description": "Maker of easy recipes & pretty photos- lover of coffee, wine & glitter. Swedish fish & travel are my love languages. Work w/ me - sweetcsdesigns@gmail.com", "url": "http://t.co/jH82b87guO", "entities": {"url": {"urls": [{"url": "http://t.co/jH82b87guO", "expanded_url": "http://sweetcsdesigns.com", "display_url": "sweetcsdesigns.com", "indices": [0, 22]}]}, "description": {"urls": []}}, "protected": false, "followers_count": 4349, "friends_count": 1020, "listed_count": 132, "created_at": "Sat May 14 14:21:31 +0000 2011", "favourites_count": 1091, "utc_offset": null, "time_zone": null, "geo_enabled": true, "verified": false, "statuses_count": 37518, "lang": "en", "contributors_enabled": false, "is_translator": false, "is_translation_enabled": false, "profile_background_color": "000000", "profile_background_image_url": "http://abs.twimg.com/images/themes/theme16/bg.gif", "profile_background_image_url_https": "https://abs.twimg.com/images/themes/theme16/bg.gif", "profile_background_tile": false, "profile_image_url": "http://pbs.twimg.com/profile_images/597392808161357824/pDclqkX-_normal.jpg", "profile_image_url_https": "https://pbs.twimg.com/profile_images/597392808161357824/pDclqkX-_normal.jpg", "profile_banner_url": "https://pbs.twimg.com/profile_banners/298548658/1486163463", "profile_link_color": "91D2FA", "profile_sidebar_border_color": "000000", "profile_sidebar_fill_color": "000000", "profile_text_color": "000000", "profile_use_background_image": false, "has_extended_profile": false, "default_profile": false, "default_profile_image": false, "following": false, "follow_request_sent": false, "notifications": false, "translator_type": "none"}, "geo": null, "coordinates": null, "place": null, "contributors": null, "retweeted_status": {"created_at": "Mon Oct 30 19:00:50 +0000 2017", "id": 925075038893682689, "id_str": "925075038893682689", "text": "Spice up your fall with this delicious and easy Spiced Apple Rum Punch with @BundabergDrinks from @WorldMarket! #ad\u2026 https://t.co/BbekQOZS93", "truncated": true, "entities": {"hashtags": [{"text": "ad", "indices": [112, 115]}], "symbols": [], "user_mentions": [{"screen_name": "BundabergDrinks", "name": "Bundaberg Drinks", "id": 303639900, "id_str": "303639900", "indices": [76, 92]}, {"screen_name": "worldmarket", "name": "World Market", "id": 21553660, "id_str": "21553660", "indices": [98, 110]}], "urls": [{"url": "https://t.co/BbekQOZS93", "expanded_url": "https://twitter.com/i/web/status/925075038893682689", "display_url": "twitter.com/i/web/status/9\u2026", "indices": [117, 140]}]}, "metadata": {"iso_language_code": "en", "result_type": "recent"}, "source": "<a href=\"http://bufferapp.com\" rel=\"nofollow\">Buffer</a>", "in_reply_to_status_id": null, "in_reply_to_status_id_str": null, "in_reply_to_user_id": null, "in_reply_to_user_id_str": null, "in_reply_to_screen_name": null, "user": {"id": 411110060, "id_str": "411110060", "name": "Kimberly Sneed", "screen_name": "ANightOwlBlog", "location": "Phoenix, AZ", "description": "#PHX \ud83c\udf35#Boymom \ud83d\udc66\ud83c\udffd\ud83d\udc66\ud83c\udffd\ud83d\udc66\ud83c\udffd #MichaelsMakers \u2702\ufe0f #Foodie \ud83c\udf79 #DisneyMoms @thedisneybelles \ud83d\udc2d #FamilyTravel \u2708\ufe0f Next: #DisneySMMC 2018! Wife to @anightowltech", "url": "https://t.co/UH02Usp16D", "entities": {"url": {"urls": [{"url": "https://t.co/UH02Usp16D", "expanded_url": "http://www.anightowlblog.com", "display_url": "anightowlblog.com", "indices": [0, 23]}]}, "description": {"urls": []}}, "protected": false, "followers_count": 46307, "friends_count": 26767, "listed_count": 481, "created_at": "Sun Nov 13 00:41:49 +0000 2011", "favourites_count": 3688, "utc_offset": -25200, "time_zone": "Arizona", "geo_enabled": true, "verified": false, "statuses_count": 45740, "lang": "en", "contributors_enabled": false, "is_translator": false, "is_translation_enabled": false, "profile_background_color": "FFF04D", "profile_background_image_url": "http://pbs.twimg.com/profile_background_images/552901855580139520/d7KJygYx.jpeg", "profile_background_image_url_https": "https://pbs.twimg.com/profile_background_images/552901855580139520/d7KJygYx.jpeg", "profile_background_tile": false, "profile_image_url": "http://pbs.twimg.com/profile_images/722236635908149248/58xmrRrF_normal.jpg", "profile_image_url_https": "https://pbs.twimg.com/profile_images/722236635908149248/58xmrRrF_normal.jpg", "profile_banner_url": "https://pbs.twimg.com/profile_banners/411110060/1508730845", "profile_link_color": "89B9B9", "profile_sidebar_border_color": "FFF8AD", "profile_sidebar_fill_color": "F6FFD1", "profile_text_color": "333333", "profile_use_background_image": true, "has_extended_profile": false, "default_profile": false, "default_profile_image": false, "following": false, "follow_request_sent": false, "notifications": false, "translator_type": "none"}, "geo": null, "coordinates": null, "place": null, "contributors": null, "is_quote_status": false, "retweet_count": 1, "favorite_count": 0, "favorited": false, "retweeted": false, "possibly_sensitive": false, "lang": "en"}, "is_quote_status": false, "retweet_count": 1, "favorite_count": 0, "favorited": false, "retweeted": false, "lang": "en"}, {"created_at": "Mon Oct 30 19:04:29 +0000 2017", "id": 925075953658843136, "id_str": "925075953658843136", "text": "Download Party @OfLincoln App https://t.co/wp2q2zpJC6 https://t.co/5Mkbjl4llX @karenhunter #civictech", "truncated": false, "entities": {"hashtags": [{"text": "civictech", "indices": [91, 101]}], "symbols": [], "user_mentions": [{"screen_name": "OfLincoln", "name": "Party of Lincoln", "id": 4730990128, "id_str": "4730990128", "indices": [15, 25]}, {"screen_name": "karenhunter", "name": "Karen Hunter", "id": 23103351, "id_str": "23103351", "indices": [78, 90]}], "urls": [{"url": "https://t.co/wp2q2zpJC6", "expanded_url": "http://bit.ly/29fj2v6", "display_url": "bit.ly/29fj2v6", "indices": [30, 53]}, {"url": "https://t.co/5Mkbjl4llX", "expanded_url": "http://apple.co/23ktVRi", "display_url": "apple.co/23ktVRi", "indices": [54, 77]}]}, "metadata": {"iso_language_code": "en", "result_type": "recent"}, "source": "<a href=\"http://bufferapp.com\" rel=\"nofollow\">Buffer</a>", "in_reply_to_status_id": null, "in_reply_to_status_id_str": null, "in_reply_to_user_id": null, "in_reply_to_user_id_str": null, "in_reply_to_screen_name": null, "user": {"id": 2293099507, "id_str": "2293099507", "name": "SiriusXM Urban View", "screen_name": "SXMUrbanView", "location": "", "description": "SiriusXM Urban View ch.126 - Conversation, information, inspiration, empowerment, motivation and companionship from the African-American perspective.", "url": "http://t.co/HOvk9z7rHM", "entities": {"url": {"urls": [{"url": "http://t.co/HOvk9z7rHM", "expanded_url": "http://www.siriusxm.com/urbanview", "display_url": "siriusxm.com/urbanview", "indices": [0, 22]}]}, "description": {"urls": []}}, "protected": false, "followers_count": 19983, "friends_count": 976, "listed_count": 176, "created_at": "Wed Jan 15 18:24:29 +0000 2014", "favourites_count": 508, "utc_offset": -14400, "time_zone": "Eastern Time (US & Canada)", "geo_enabled": true, "verified": true, "statuses_count": 26651, "lang": "en", "contributors_enabled": false, "is_translator": false, "is_translation_enabled": false, "profile_background_color": "131516", "profile_background_image_url": "http://abs.twimg.com/images/themes/theme14/bg.gif", "profile_background_image_url_https": "https://abs.twimg.com/images/themes/theme14/bg.gif", "profile_background_tile": true, "profile_image_url": "http://pbs.twimg.com/profile_images/606884198683508737/R1Oj8Lz9_normal.png", "profile_image_url_https": "https://pbs.twimg.com/profile_images/606884198683508737/R1Oj8Lz9_normal.png", "profile_banner_url": "https://pbs.twimg.com/profile_banners/2293099507/1389812075", "profile_link_color": "009999", "profile_sidebar_border_color": "EEEEEE", "profile_sidebar_fill_color": "EFEFEF", "profile_text_color": "333333", "profile_use_background_image": true, "has_extended_profile": false, "default_profile": false, "default_profile_image": false, "following": false, "follow_request_sent": false, "notifications": false, "translator_type": "none"}, "geo": null, "coordinates": null, "place": null, "contributors": null, "is_quote_status": false, "retweet_count": 0, "favorite_count": 0, "favorited": false, "retweeted": false, "possibly_sensitive": false, "lang": "en"}, {"created_at": "Mon Oct 30 19:04:29 +0000 2017", "id": 925075953612619777, "id_str": "925075953612619777", "text": "J\u2019veux qu\u2019on me pt les reins sur ce son https://t.co/vI6FSHL3am", "truncated": false, "entities": {"hashtags": [], "symbols": [], "user_mentions": [], "urls": [{"url": "https://t.co/vI6FSHL3am", "expanded_url": "https://itunes.apple.com/fr/album/life/id1296240468?i=1296240469&l=en", "display_url": "itunes.apple.com/fr/album/life/\u2026", "indices": [40, 63]}]}, "metadata": {"iso_language_code": "fr", "result_type": "recent"}, "source": "<a href=\"http://twitter.com/download/iphone\" rel=\"nofollow\">Twitter for iPhone</a>", "in_reply_to_status_id": null, "in_reply_to_status_id_str": null, "in_reply_to_user_id": null, "in_reply_to_user_id_str": null, "in_reply_to_screen_name": null, "user": {"id": 126893790, "id_str": "126893790", "name": "\ud83d\udc80 row", "screen_name": "chebeuh", "location": "sa\u00efd", "description": "Tattoo Artist https://t.co/x7ULdzfKeq", "url": "https://t.co/i5YNl4AT1E", "entities": {"url": {"urls": [{"url": "https://t.co/i5YNl4AT1E", "expanded_url": "https://chebeuharts.wixsite.com/book", "display_url": "chebeuharts.wixsite.com/book", "indices": [0, 23]}]}, "description": {"urls": [{"url": "https://t.co/x7ULdzfKeq", "expanded_url": "https://www.instagram.com/chebeuh/", "display_url": "instagram.com/chebeuh/", "indices": [14, 37]}]}}, "protected": false, "followers_count": 2324, "friends_count": 677, "listed_count": 54, "created_at": "Sat Mar 27 09:52:26 +0000 2010", "favourites_count": 22865, "utc_offset": 3600, "time_zone": "Paris", "geo_enabled": true, "verified": false, "statuses_count": 209077, "lang": "fr", "contributors_enabled": false, "is_translator": false, "is_translation_enabled": false, "profile_background_color": "FFFFFF", "profile_background_image_url": "http://pbs.twimg.com/profile_background_images/617467743273680896/eAaV3eLI.jpg", "profile_background_image_url_https": "https://pbs.twimg.com/profile_background_images/617467743273680896/eAaV3eLI.jpg", "profile_background_tile": false, "profile_image_url": "http://pbs.twimg.com/profile_images/920765696342220801/iI4248TL_normal.jpg", "profile_image_url_https": "https://pbs.twimg.com/profile_images/920765696342220801/iI4248TL_normal.jpg", "profile_banner_url": "https://pbs.twimg.com/profile_banners/126893790/1508066654", "profile_link_color": "ABB8C2", "profile_sidebar_border_color": "FFFFFF", "profile_sidebar_fill_color": "88E016", "profile_text_color": "05F0AD", "profile_use_background_image": true, "has_extended_profile": true, "default_profile": false, "default_profile_image": false, "following": false, "follow_request_sent": false, "notifications": false, "translator_type": "regular"}, "geo": null, "coordinates": null, "place": null, "contributors": null, "is_quote_status": false, "retweet_count": 0, "favorite_count": 0, "favorited": false, "retweeted": false, "possibly_sensitive": false, "lang": "fr"}], "search_metadata": {"completed_in": 0.05, "max_id": 925075964287246337, "max_id_str": "925075964287246337", "next_results": "?max_id=925075953612619776&q=apple&include_entities=1", "query": "apple", "refresh_url": "?since_id=925075964287246337&q=apple&include_entities=1", "count": 15, "since_id": 0, "since_id_str": "0"}}
